genie_python/.pylintrc
genie_python/__init__.py
genie_python/_version.py
genie_python/block_names.py
genie_python/channel_access_exceptions.py
genie_python/genie.py
genie_python/genie_advanced.py
genie_python/genie_alerts.py
genie_python/genie_api_setup.py
genie_python/genie_blockserver.py
genie_python/genie_cachannel_wrapper.py
genie_python/genie_change_cache.py
genie_python/genie_dae.py
genie_python/genie_epics_api.py
genie_python/genie_experimental_data.py
genie_python/genie_logging.py
genie_python/genie_p4p_wrapper.py
genie_python/genie_plot.py
genie_python/genie_pre_post_cmd_manager.py
genie_python/genie_pv_connection_protocol.py
genie_python/genie_script_checker.py
genie_python/genie_script_generator.py
genie_python/genie_simulate.py
genie_python/genie_simulate_impl.py
genie_python/genie_startup.py
genie_python/genie_toggle_settings.py
genie_python/genie_wait_for_move.py
genie_python/genie_waitfor.py
genie_python/mysql_abstraction_layer.py
genie_python/scanning_instrument_pylint_plugin.py
genie_python/utilities.py
genie_python/version.py
genie_python/matplotlib_backend/__init__.py
genie_python/matplotlib_backend/ibex_websocket_backend.py
genie_python/testing_utils/__init__.py
genie_python/testing_utils/script_checker.py
genie_python/typings/CaChannel/CaChannel.pyi
genie_python/typings/CaChannel/__init__.pyi
genie_python/typings/CaChannel/_version.pyi
genie_python/typings/CaChannel/ca.pyi
genie_python-26.2.0.dist-info/licenses/LICENSE
genie_python-26.2.0.dist-info/METADATA
genie_python-26.2.0.dist-info/WHEEL
genie_python-26.2.0.dist-info/top_level.txt
genie_python-26.2.0.dist-info/RECORD
